README
setup.cfg
setup.py
mozscreenshots/__init__.py
mozscreenshots/compare_screenshots.py
mozscreenshots/fetch_screenshots.py
mozscreenshots/list_nightlies.py
mozscreenshots/prefs.json
mozscreenshots/runner.py
mozscreenshots.egg-info/PKG-INFO
mozscreenshots.egg-info/SOURCES.txt
mozscreenshots.egg-info/dependency_links.txt
mozscreenshots.egg-info/entry_points.txt
mozscreenshots.egg-info/not-zip-safe
mozscreenshots.egg-info/requires.txt
mozscreenshots.egg-info/top_level.txt
mozscreenshots/extension/configurations/AppMenu.jsm
mozscreenshots/extension/configurations/Buttons.jsm
mozscreenshots/extension/configurations/ControlCenter.jsm
mozscreenshots/extension/configurations/CustomizeMode.jsm
mozscreenshots/extension/configurations/DevEdition.jsm
mozscreenshots/extension/configurations/DevTools.jsm
mozscreenshots/extension/configurations/LightweightThemes.jsm
mozscreenshots/extension/configurations/PermissionPrompts.jsm
mozscreenshots/extension/configurations/Preferences.jsm
mozscreenshots/extension/configurations/PrivateBrowsing.jsm
mozscreenshots/extension/configurations/SystemTheme.jsm
mozscreenshots/extension/configurations/Tabs.jsm
mozscreenshots/extension/configurations/TabsInTitlebar.jsm
mozscreenshots/extension/configurations/Toolbars.jsm
mozscreenshots/extension/configurations/WebNotifications.jsm
mozscreenshots/extension/configurations/WindowSize.jsm
mozscreenshots/extension/lib/ChangeWindowsTheme.bat
mozscreenshots/extension/lib/CloseDisplayProperties.vbs