Metadata-Version: 1.1
Name: mozscreenshots
Version: 0.4.0
Summary: Takes screenshots of different states of a Mozilla application
Home-page: https://github.com/mnoorenberghe/mozscreenshots
Author: Matthew Noorenberghe
Author-email: MattN+mozscreenshots@mozilla.com
License: MPL 2.0
Download-URL: https://github.com/mnoorenberghe/mozscreenshots/tarball/0.4.0
Keywords: mozilla,screenshots,Firefox
Platform: UNKNOWN
Classifier: Environment :: Console
Classifier: Intended Audience :: Developers
Classifier: License :: OSI Approved :: Mozilla Public License 2.0 (MPL 2.0)
Classifier: Natural Language :: English
Classifier: Operating System :: OS Independent
Classifier: Programming Language :: JavaScript
Classifier: Programming Language :: Python
Classifier: Topic :: Software Development :: Libraries :: Python Modules
